CompetitionAssay/__init__.py
CompetitionAssay/binarization.py
CompetitionAssay/datahandling.py
CompetitionAssay/denoising.py
CompetitionAssay/quantification.py
CompetitionAssay/visualization.py
competitionassay-0.0.5.dist-info/LICENSE
competitionassay-0.0.5.dist-info/METADATA
competitionassay-0.0.5.dist-info/WHEEL
competitionassay-0.0.5.dist-info/top_level.txt
competitionassay-0.0.5.dist-info/RECORD
