Metadata-Version: 2.1
Name: competitionassay
Version: 0.0.5
Summary: Software for the analysis of competition assay data.
Home-page: https://github.com/Nablaaa/CompetitionAssay
Author: Eric Schmidt
Author-email: eric_schmidt_99@gmx.de
License: UNKNOWN
Platform: UNKNOWN
Classifier: Programming Language :: Python :: 3
Classifier: Operating System :: OS Independent
Requires-Python: >=3.9
License-File: LICENSE
Requires-Dist: absl-py ==2.0.0
Requires-Dist: alabaster ==0.7.13
Requires-Dist: app-model ==0.2.2
Requires-Dist: appdirs ==1.4.4
Requires-Dist: asttokens ==2.4.1
Requires-Dist: astunparse ==1.6.3
Requires-Dist: attrs ==23.1.0
Requires-Dist: Babel ==2.13.1
Requires-Dist: build ==1.0.3
Requires-Dist: cachetools ==5.3.2
Requires-Dist: cachey ==0.2.1
Requires-Dist: certifi ==2023.7.22
Requires-Dist: charset-normalizer ==3.3.2
Requires-Dist: click ==8.1.7
Requires-Dist: cloudpickle ==3.0.0
Requires-Dist: comm ==0.2.0
Requires-Dist: contourpy ==1.2.0
Requires-Dist: csbdeep ==0.7.4
Requires-Dist: cycler ==0.12.1
Requires-Dist: dask ==2023.10.1
Requires-Dist: debugpy ==1.8.0
Requires-Dist: decorator ==5.1.1
Requires-Dist: docstring-parser ==0.15
Requires-Dist: docutils ==0.17.1
Requires-Dist: exceptiongroup ==1.1.3
Requires-Dist: executing ==2.0.1
Requires-Dist: flatbuffers ==23.5.26
Requires-Dist: fonttools ==4.44.0
Requires-Dist: freetype-py ==2.4.0
Requires-Dist: fsspec ==2023.10.0
Requires-Dist: gast ==0.4.0
Requires-Dist: google-auth ==2.23.4
Requires-Dist: google-auth-oauthlib ==1.0.0
Requires-Dist: google-pasta ==0.2.0
Requires-Dist: grpcio ==1.59.2
Requires-Dist: h5py ==3.10.0
Requires-Dist: HeapDict ==1.0.1
Requires-Dist: hsluv ==5.0.4
Requires-Dist: idna ==3.4
Requires-Dist: imagecodecs ==2023.9.18
Requires-Dist: imageio ==2.32.0
Requires-Dist: imagesize ==1.4.1
Requires-Dist: importlib-metadata ==6.8.0
Requires-Dist: importlib-resources ==6.1.0
Requires-Dist: in-n-out ==0.1.9
Requires-Dist: ipykernel ==6.26.0
Requires-Dist: ipython ==8.17.2
Requires-Dist: jax ==0.4.20
Requires-Dist: jedi ==0.19.1
Requires-Dist: Jinja2 ==3.1.2
Requires-Dist: joblib ==1.3.2
Requires-Dist: jsonschema ==4.19.2
Requires-Dist: jsonschema-specifications ==2023.7.1
Requires-Dist: jupyter-client ==8.6.0
Requires-Dist: jupyter-core ==5.5.0
Requires-Dist: keras ==2.12.0
Requires-Dist: kiwisolver ==1.4.5
Requires-Dist: lazy-loader ==0.3
Requires-Dist: libclang ==16.0.6
Requires-Dist: locket ==1.0.0
Requires-Dist: magicgui ==0.8.0
Requires-Dist: Markdown ==3.5.1
Requires-Dist: markdown-it-py ==3.0.0
Requires-Dist: MarkupSafe ==2.1.3
Requires-Dist: matplotlib ==3.8.1
Requires-Dist: matplotlib-inline ==0.1.6
Requires-Dist: mdurl ==0.1.2
Requires-Dist: ml-dtypes ==0.3.1
Requires-Dist: mypy-extensions ==1.0.0
Requires-Dist: nest-asyncio ==1.5.8
Requires-Dist: networkx ==3.2.1
Requires-Dist: npe2 ==0.7.3
Requires-Dist: numpy ==1.23.5
Requires-Dist: numpydoc ==1.5.0
Requires-Dist: oauthlib ==3.2.2
Requires-Dist: opt-einsum ==3.3.0
Requires-Dist: packaging ==23.2
Requires-Dist: pandas ==2.1.2
Requires-Dist: parso ==0.8.3
Requires-Dist: partd ==1.4.1
Requires-Dist: pexpect ==4.8.0
Requires-Dist: Pillow ==10.0.1
Requires-Dist: Pint ==0.22
Requires-Dist: platformdirs ==3.11.0
Requires-Dist: polars ==0.19.12
Requires-Dist: pooch ==1.8.0
Requires-Dist: prompt-toolkit ==3.0.39
Requires-Dist: protobuf ==4.25.0
Requires-Dist: psutil ==5.9.6
Requires-Dist: psygnal ==0.9.4
Requires-Dist: ptyprocess ==0.7.0
Requires-Dist: pure-eval ==0.2.2
Requires-Dist: pyarrow ==14.0.0
Requires-Dist: pyasn1 ==0.5.0
Requires-Dist: pyasn1-modules ==0.3.0
Requires-Dist: pyconify ==0.1.6
Requires-Dist: pydantic ==1.10.13
Requires-Dist: Pygments ==2.16.1
Requires-Dist: PyOpenGL ==3.1.7
Requires-Dist: pyparsing ==3.1.1
Requires-Dist: pyproject-hooks ==1.0.0
Requires-Dist: PyQt5 ==5.15.10
Requires-Dist: PyQt5-Qt5 ==5.15.2
Requires-Dist: PyQt5-sip ==12.13.0
Requires-Dist: python-dateutil ==2.8.2
Requires-Dist: pytz ==2023.3.post1
Requires-Dist: PyYAML ==6.0.1
Requires-Dist: pyzmq ==25.1.1
Requires-Dist: qtconsole ==5.5.0
Requires-Dist: QtPy ==2.4.1
Requires-Dist: referencing ==0.30.2
Requires-Dist: requests ==2.31.0
Requires-Dist: requests-oauthlib ==1.3.1
Requires-Dist: rich ==13.6.0
Requires-Dist: rpds-py ==0.12.0
Requires-Dist: rsa ==4.9
Requires-Dist: ruamel.yaml ==0.18.5
Requires-Dist: ruamel.yaml.clib ==0.2.8
Requires-Dist: scikit-image ==0.22.0
Requires-Dist: scikit-learn ==1.1.3
Requires-Dist: scipy ==1.11.3
Requires-Dist: six ==1.16.0
Requires-Dist: snowballstemmer ==2.2.0
Requires-Dist: Sphinx ==4.5.0
Requires-Dist: sphinxcontrib-applehelp ==1.0.4
Requires-Dist: sphinxcontrib-devhelp ==1.0.2
Requires-Dist: sphinxcontrib-htmlhelp ==2.0.1
Requires-Dist: sphinxcontrib-jsmath ==1.0.1
Requires-Dist: sphinxcontrib-qthelp ==1.0.3
Requires-Dist: sphinxcontrib-serializinghtml ==1.1.5
Requires-Dist: stack-data ==0.6.3
Requires-Dist: superqt ==0.6.1
Requires-Dist: termcolor ==2.3.0
Requires-Dist: threadpoolctl ==3.2.0
Requires-Dist: tifffile ==2023.9.26
Requires-Dist: tomli ==2.0.1
Requires-Dist: tomli-w ==1.0.0
Requires-Dist: toolz ==0.12.0
Requires-Dist: tornado ==6.3.3
Requires-Dist: tqdm ==4.66.1
Requires-Dist: traitlets ==5.13.0
Requires-Dist: typer ==0.9.0
Requires-Dist: typing-extensions ==4.8.0
Requires-Dist: tzdata ==2023.3
Requires-Dist: urllib3 ==2.0.7
Requires-Dist: vispy ==0.12.2
Requires-Dist: wcwidth ==0.2.9
Requires-Dist: Werkzeug ==3.0.1
Requires-Dist: wrapt ==1.14.1
Requires-Dist: zipp ==3.17.0
Provides-Extra: all
Requires-Dist: tensorflow ==2.12.0 ; extra == 'all'
Requires-Dist: napari ==0.4.18 ; extra == 'all'
Requires-Dist: n2v ==0.3.2 ; extra == 'all'
